[
  {
    "product_id": "regular-user-repo-id",
    "account_id": "create-repositories-user",
    "title": "Regular",
    "description": "Regular user's repository",
    "created_at": "2020-01-01T00:00:00Z",
    "updated_at": "2020-01-01T00:00:00Z",
    "visibility": "public",
    "metadata": {
      "mirrors": {
        "primary-data-connection": {
          "storage_type": "s3",
          "connection_id": "primary-data-connection",
          "prefix": "create-repositories-user/regular-user-repo-id/",
          "config": {
            "region": "us-east-1",
            "bucket": "source-coop-data"
          },
          "is_primary": true,
          "sync_status": {
            "last_sync_at": "2020-01-01T00:00:00Z",
            "is_synced": true
          },
          "stats": {
            "total_objects": 100,
            "total_size": 1024000,
            "last_verified_at": "2020-01-01T00:00:00Z"
          }
        }
      },
      "primary_mirror": "primary-data-connection",
      "tags": ["mock"],
      "roles": {}
    }
  },
  {
    "product_id": "org-repo-id",
    "account_id": "organization",
    "title": "Organization",
    "description": "Organization's repository",
    "created_at": "2020-01-01T00:00:00Z",
    "updated_at": "2020-01-01T00:00:00Z",
    "visibility": "public",
    "metadata": {
      "mirrors": {
        "primary-data-connection": {
          "storage_type": "s3",
          "connection_id": "primary-data-connection",
          "prefix": "organization/org-repo-id/",
          "config": {
            "region": "us-east-1",
            "bucket": "source-coop-data"
          },
          "is_primary": true,
          "sync_status": {
            "last_sync_at": "2020-01-01T00:00:00Z",
            "is_synced": true
          },
          "stats": {
            "total_objects": 150,
            "total_size": 2048000,
            "last_verified_at": "2020-01-01T00:00:00Z"
          }
        }
      },
      "primary_mirror": "primary-data-connection",
      "tags": ["mock"],
      "roles": {}
    }
  },
  {
    "product_id": "disabled-org-repo-id",
    "account_id": "organization",
    "title": "Disabled Repo",
    "description": "Disabled Organization's repository",
    "created_at": "2020-01-01T00:00:00Z",
    "updated_at": "2020-01-01T00:00:00Z",
    "visibility": "restricted",
    "metadata": {
      "mirrors": {
        "primary-data-connection": {
          "storage_type": "s3",
          "connection_id": "primary-data-connection",
          "prefix": "organization/disabled-org-repo-id/",
          "config": {
            "region": "us-east-1",
            "bucket": "source-coop-data"
          },
          "is_primary": true,
          "sync_status": {
            "last_sync_at": "2020-01-01T00:00:00Z",
            "is_synced": false,
            "error": "Repository disabled"
          },
          "stats": {
            "total_objects": 0,
            "total_size": 0,
            "last_verified_at": "2020-01-01T00:00:00Z"
          }
        }
      },
      "primary_mirror": "primary-data-connection",
      "tags": ["mock"],
      "roles": {}
    }
  },
  {
    "product_id": "unlisted-org-repo-id",
    "account_id": "organization",
    "title": "Unlisted Repo",
    "description": "Unlisted Organization's repository",
    "created_at": "2020-01-01T00:00:00Z",
    "updated_at": "2020-01-01T00:00:00Z",
    "visibility": "unlisted",
    "metadata": {
      "mirrors": {
        "primary-data-connection": {
          "storage_type": "s3",
          "connection_id": "primary-data-connection",
          "prefix": "organization/unlisted-org-repo-id/",
          "config": {
            "region": "us-east-1",
            "bucket": "source-coop-data"
          },
          "is_primary": true,
          "sync_status": {
            "last_sync_at": "2020-01-01T00:00:00Z",
            "is_synced": true
          },
          "stats": {
            "total_objects": 75,
            "total_size": 512000,
            "last_verified_at": "2020-01-01T00:00:00Z"
          }
        }
      },
      "primary_mirror": "primary-data-connection",
      "tags": ["mock"],
      "roles": {}
    }
  },
  {
    "product_id": "featured-org-repo-id",
    "account_id": "organization",
    "title": "Featured Repo",
    "description": "Featured Organization's repository",
    "created_at": "2020-01-01T00:00:00Z",
    "updated_at": "2020-01-01T00:00:00Z",
    "visibility": "public",
    "metadata": {
      "mirrors": {
        "primary-data-connection": {
          "storage_type": "s3",
          "connection_id": "primary-data-connection",
          "prefix": "organization/featured-org-repo-id/",
          "config": {
            "region": "us-east-1",
            "bucket": "source-coop-data"
          },
          "is_primary": true,
          "sync_status": {
            "last_sync_at": "2020-01-01T00:00:00Z",
            "is_synced": true
          },
          "stats": {
            "total_objects": 200,
            "total_size": 4096000,
            "last_verified_at": "2020-01-01T00:00:00Z"
          }
        }
      },
      "primary_mirror": "primary-data-connection",
      "tags": ["mock", "featured"],
      "roles": {}
    }
  },
  {
    "product_id": "private-org-repo-id",
    "account_id": "organization",
    "title": "Private Repo",
    "description": "Private Organization's repository",
    "created_at": "2020-01-01T00:00:00Z",
    "updated_at": "2020-01-01T00:00:00Z",
    "visibility": "restricted",
    "metadata": {
      "mirrors": {
        "primary-data-connection": {
          "storage_type": "s3",
          "connection_id": "primary-data-connection",
          "prefix": "organization/private-org-repo-id/",
          "config": {
            "region": "us-east-1",
            "bucket": "source-coop-data"
          },
          "is_primary": true,
          "sync_status": {
            "last_sync_at": "2020-01-01T00:00:00Z",
            "is_synced": true
          },
          "stats": {
            "total_objects": 50,
            "total_size": 256000,
            "last_verified_at": "2020-01-01T00:00:00Z"
          }
        }
      },
      "primary_mirror": "primary-data-connection",
      "tags": ["mock", "private"],
      "roles": {
        "organization": {
          "account_id": "organization",
          "role": "admin",
          "granted_at": "2020-01-01T00:00:00Z",
          "granted_by": "organization"
        }
      }
    }
  },
  {
    "product_id": "subscription-org-repo-id",
    "account_id": "organization",
    "title": "Subscription Repo",
    "description": "Subscription Organization's repository",
    "created_at": "2020-01-01T00:00:00Z",
    "updated_at": "2020-01-01T00:00:00Z",
    "visibility": "restricted",
    "metadata": {
      "mirrors": {
        "primary-data-connection": {
          "storage_type": "s3",
          "connection_id": "primary-data-connection",
          "prefix": "organization/subscription-org-repo-id/",
          "config": {
            "region": "us-east-1",
            "bucket": "source-coop-data"
          },
          "is_primary": true,
          "sync_status": {
            "last_sync_at": "2020-01-01T00:00:00Z",
            "is_synced": true
          },
          "stats": {
            "total_objects": 300,
            "total_size": 8192000,
            "last_verified_at": "2020-01-01T00:00:00Z"
          }
        }
      },
      "primary_mirror": "primary-data-connection",
      "tags": ["mock", "subscription"],
      "roles": {
        "organization": {
          "account_id": "organization",
          "role": "admin",
          "granted_at": "2020-01-01T00:00:00Z",
          "granted_by": "organization"
        }
      }
    }
  }
]
